meu_contracheque/__init__.py
meu_contracheque/cli.py
meu_contracheque/mg_all_periods.py
meu_contracheque/mg_initial_period.py
meu_contracheque/mg_last_period.py
meu_contracheque/scraping_mg.py
meu_contracheque/time_reader.py
meu_contracheque-0.3.1.dist-info/LICENCE.txt
meu_contracheque-0.3.1.dist-info/METADATA
meu_contracheque-0.3.1.dist-info/WHEEL
meu_contracheque-0.3.1.dist-info/entry_points.txt
meu_contracheque-0.3.1.dist-info/top_level.txt
meu_contracheque-0.3.1.dist-info/RECORD
