Metadata-Version: 2.1
Name: meu-contracheque
Version: 0.3.1
Summary: Buscar informações de contracheques via web scraping
Home-page: https://github.com/gabrielbdornas/meu-contracheque
Author: Gabriel Braico Dornas
Author-email: gabrielbdornas@gmail.com
License: UNKNOWN
Keywords: python,Minas Gerais,Contracheque
Platform: UNKNOWN
Classifier: Development Status :: 1 - Planning
Classifier: Intended Audience :: Developers
Classifier: Programming Language :: Python :: 3
Classifier: Operating System :: Unix
Classifier: Operating System :: MacOS :: MacOS X
Classifier: Operating System :: Microsoft :: Windows
License-File: LICENCE.txt
Requires-Dist: Unidecode (==1.3.6)
Requires-Dist: bs4 (==0.0.1)
Requires-Dist: click (==8.0.1)
Requires-Dist: html5lib (==1.1)
Requires-Dist: python-dateutil (==2.8.2)
Requires-Dist: python-dotenv (==0.19.2)
Requires-Dist: selenium (==4.0.0)
